powermem_mcp/__init__.py
powermem_mcp/__main__.py
powermem_mcp/server.py
powermem_mcp-0.2.0.dist-info/licenses/LICENSE
powermem_mcp-0.2.0.dist-info/METADATA
powermem_mcp-0.2.0.dist-info/WHEEL
powermem_mcp-0.2.0.dist-info/entry_points.txt
powermem_mcp-0.2.0.dist-info/top_level.txt
powermem_mcp-0.2.0.dist-info/RECORD
