Metadata-Version: 2.4
Name: powermem-mcp
Version: 0.2.0
Summary: PowerMem MCP Server - Model Context Protocol server for PowerMem memory management
Home-page: https://github.com/oceanbase/powermem
Author: powermem Team
Author-email: powermem Team <team@powermem.ai>
Maintainer-email: powermem Team <team@powermem.ai>
License: Apache-2.0
Project-URL: Bug Reports, https://github.com/oceanbase/powermem/issues
Project-URL: Source, https://github.com/oceanbase/powermem
Project-URL: Documentation, https://powermem.ai/docs
Keywords: powermem,mcp,memory,ai,llm,vector-database
Classifier: Development Status :: 3 - Alpha
Classifier: Intended Audience :: Developers
Classifier: Operating System :: OS Independent
Classifier: Programming Language :: Python :: 3
Classifier: Programming Language :: Python :: 3.10
Classifier: Programming Language :: Python :: 3.11
Classifier: Programming Language :: Python :: 3.12
Classifier: Topic :: Software Development :: Libraries :: Python Modules
Classifier: Topic :: Scientific/Engineering :: Artificial Intelligence
Requires-Python: >=3.10
License-File: LICENSE
Requires-Dist: powermem>=0.2.0
Requires-Dist: fastmcp>=1.0
Requires-Dist: uvicorn>=0.27.1
Requires-Dist: tomli>=1.2.0; python_version < "3.11"
Provides-Extra: dev
Requires-Dist: pytest>=7.0.0; extra == "dev"
Requires-Dist: pytest-asyncio>=0.21.0; extra == "dev"
Requires-Dist: black>=22.0.0; extra == "dev"
Requires-Dist: flake8>=4.0.0; extra == "dev"
Requires-Dist: mypy>=0.991; extra == "dev"
Requires-Dist: build>=0.10.0; extra == "dev"
Requires-Dist: twine>=4.0.0; extra == "dev"
Provides-Extra: test
Requires-Dist: pytest>=7.0.0; extra == "test"
Requires-Dist: pytest-asyncio>=0.21.0; extra == "test"
Requires-Dist: pytest-cov>=4.0.0; extra == "test"
Dynamic: author
Dynamic: home-page
Dynamic: license-file
Dynamic: requires-python
